repathlib/__init__.py
repathlib/repathlib.py
repathlib-0.1.5.dist-info/LICENSE
repathlib-0.1.5.dist-info/METADATA
repathlib-0.1.5.dist-info/WHEEL
repathlib-0.1.5.dist-info/top_level.txt
repathlib-0.1.5.dist-info/RECORD
