Metadata-Version: 2.1
Name: repathlib
Version: 0.1.5
Summary: pathlib with regular expressions
Home-page: https://repathlib.readthedocs.io/en/latest/
Author: Matthew Badger
License: UNKNOWN
Platform: UNKNOWN
